documenter.py
docstring_cli-1.0.0.dist-info/METADATA
docstring_cli-1.0.0.dist-info/WHEEL
docstring_cli-1.0.0.dist-info/entry_points.txt
docstring_cli-1.0.0.dist-info/top_level.txt
docstring_cli-1.0.0.dist-info/RECORD
