Metadata-Version: 2.4
Name: docstring-cli
Version: 1.0.0
Summary: Simple CLI to add docstrings to Python code
Home-page: https://github.com/vijasuryabaka/Docstring_CLI
Author: Vijaysurya
Author-email: Vijay <vijay@example.com>
Requires-Python: >=3.8
Requires-Dist: requests>=2.25.0
Dynamic: author
Dynamic: home-page
